[
    {
        "title": "Hello !",
        "subtitle": "Bienvenue sur mon portfolio",
        "intro": "Lorem ipsum dolor sit amet consectetur adipisicing elit. Ipsa deserunt illo possimus suscipit quas tempore veritatis laborum. Facilis voluptate enim cum officiis porro dolore blanditiis ipsum autem ratione alias, corrupti sint aliquid velit quibusdam nesciunt dignissimos commodi voluptatibus qui molestias aut. Ducimus dolor iste iure deleniti repellendus ea accusantium, obcaecati eaque sequi architecto alias optio nihil. Laudantium excepturi, rem eum minima architecto perferendis animi non possimus nemo quidem quae mollitia inventore! Blanditiis natus minus dolorem non veritatis error incidunt! Accusantium qui aliquam voluptatem explicabo natus vitae doloremque exercitationem laudantium in fugiat, deserunt odio ullam deleniti quaerat totam consequatur rem pariatur.",
        "picture": {
            "src": "/static/media/IMG_1903.70286ca597aee710a918.jpeg",
            "alt": "Photo de Hervé Boulangué, developpeur Frontend"
        },
        "skillsSubtitle": "Mes compétences :",
        "skillsList": [
            {
                "logo": "/static/media/logo-1.b879f838faf1cb951d1c2230fd933a39.svg",
                "alt": "Logo de la technologie Javascript",
                "name": "Javascript"
            },
            {
                "logo": "/static/media/logo-2.f318c8b1d5945fa9adc827ae94849cb1.svg",
                "alt": "Logo de la technologie HTML",
                "name": "HTML"
            },
            {
                "logo": "/static/media/logo-3.4e47c3122b8d2476a02f97dcfcb28640.svg",
                "alt": "Logo de la technologie CSS",
                "name": "CSS"
            },
            {
                "logo": "/static/media/logo-4.8aa78a8393470431c8036541f0708bd7.svg",
                "alt": "Logo de la technologie SASS",
                "name": "SASS"
            },
            {
                "logo": "/static/media/logo-5.4f3c72c16844c2ae308bed34e6b242f9.svg",
                "alt": "Logo de la technologie NodeJS",
                "name": "Node JS"
            },
            {
                "logo": "/static/media/logo-6.1aca075d5cce0819fea7ea0902d94ce4.svg",
                "alt": "Logo de la technologie Mongo DB",
                "name": "Mongo DB"
            },
            {
                "logo": "/static/media/logo-7.e0d7d7254ac0545743fc7af09c1e977b.svg",
                "alt": "Logo de la technologie GitHub",
                "name": "GitHub"
            },
            {
                "logo": "/static/media/logo-8.903d77ad940b12efaddde2484397ad4a.svg",
                "alt": "Logo de la technologie React",
                "name": "React"
            }
        ]
    }
]